tastyapi/__init__.py
tastyapi/command_line.py
tastyapi/main.py
tastyapi-0.3.1.dist-info/DESCRIPTION.rst
tastyapi-0.3.1.dist-info/METADATA
tastyapi-0.3.1.dist-info/RECORD
tastyapi-0.3.1.dist-info/WHEEL
tastyapi-0.3.1.dist-info/entry_points.txt
tastyapi-0.3.1.dist-info/metadata.json
tastyapi-0.3.1.dist-info/top_level.txt
