Metadata-Version: 2.0
Name: tastyapi
Version: 0.3.1
Summary: Python wrapper for Tastynode API
Home-page: https://tastynode.com
Author: sssssss340
Author-email: viis340@gmail.com
License: UNKNOWN
Platform: UNKNOWN
Requires-Dist: requests
